<?xml version="1.0" encoding="utf-8"?>
<abapGit version="v1.0.0" serializer="LCL_OBJECT_SSST" serializer_version="v1.0.0">
 <asx:abap xmlns:asx="http://www.sap.com/abapxml" version="1.0">
  <asx:values>
   <HEADER>
    <STYLENAME>ZSDSSD010</STYLENAME>
    <MASTERLANG>E</MASTERLANG>
    <LANGU>E</LANGU>
    <CAPTION>Style ZSDSSD_LOGISTIC_FORM</CAPTION>
    <V_CAPTION>Style ZSDSSD_LOGISTIC_FORM</V_CAPTION>
    <TDFIRSTPAR>L</TDFIRSTPAR>
    <CPI>10.0</CPI>
    <LPI>6.0</LPI>
    <TDTABDIST>1.0</TDTABDIST>
    <TDTABDISTU>CM</TDTABDISTU>
    <ACTIVE>A</ACTIVE>
    <TDFAMILY>COURIER</TDFAMILY>
    <TDHEIGHT>120</TDHEIGHT>
   </HEADER>
   <SSFPARAS>
    <SSFPARAS>
     <ACTIVE>A</ACTIVE>
     <STYLENAME>ZSDSSD010</STYLENAME>
     <TDPARGRAPH>C1</TDPARGRAPH>
     <TDPJUSTIFY>CENTER</TDPJUSTIFY>
     <TDPLDIST>1.0</TDPLDIST>
     <TDPLDISTU>LN</TDPLDISTU>
     <TDPTOPU>CM</TDPTOPU>
     <TDPBOTU>CM</TDPBOTU>
     <TDPLEFTU>CM</TDPLEFTU>
     <TDPRIGHTU>CM</TDPRIGHTU>
     <TDPENTRYU>CM</TDPENTRYU>
     <TDFAMILY>THANGSAN</TDFAMILY>
     <TDHEIGHT>160</TDHEIGHT>
     <TDBOLD>X</TDBOLD>
     <TDITALIC>*</TDITALIC>
     <TDUNDERLIN>*</TDUNDERLIN>
     <LANGU>E</LANGU>
    </SSFPARAS>
    <SSFPARAS>
     <ACTIVE>A</ACTIVE>
     <STYLENAME>ZSDSSD010</STYLENAME>
     <TDPARGRAPH>C2</TDPARGRAPH>
     <TDPJUSTIFY>CENTER</TDPJUSTIFY>
     <TDPLDIST>1.0</TDPLDIST>
     <TDPLDISTU>LN</TDPLDISTU>
     <TDPTOP>0.2</TDPTOP>
     <TDPTOPU>CM</TDPTOPU>
     <TDPBOTU>CM</TDPBOTU>
     <TDPLEFTU>CM</TDPLEFTU>
     <TDPRIGHTU>CM</TDPRIGHTU>
     <TDPENTRYU>CM</TDPENTRYU>
     <TDFAMILY>THANGSAN</TDFAMILY>
     <TDHEIGHT>160</TDHEIGHT>
     <TDBOLD>X</TDBOLD>
     <TDITALIC>*</TDITALIC>
     <TDUNDERLIN>*</TDUNDERLIN>
     <LANGU>E</LANGU>
    </SSFPARAS>
    <SSFPARAS>
     <ACTIVE>A</ACTIVE>
     <STYLENAME>ZSDSSD010</STYLENAME>
     <TDPARGRAPH>C3</TDPARGRAPH>
     <TDPJUSTIFY>CENTER</TDPJUSTIFY>
     <TDPLDIST>0.5</TDPLDIST>
     <TDPLDISTU>LN</TDPLDISTU>
     <TDPTOP>0.1</TDPTOP>
     <TDPTOPU>CM</TDPTOPU>
     <TDPBOTU>CM</TDPBOTU>
     <TDPLEFTU>CM</TDPLEFTU>
     <TDPRIGHTU>CM</TDPRIGHTU>
     <TDPENTRYU>CM</TDPENTRYU>
     <TDNUMLEFTU>CM</TDNUMLEFTU>
     <TDFAMILY>THANGSAN</TDFAMILY>
     <TDHEIGHT>120</TDHEIGHT>
     <TDBOLD>*</TDBOLD>
     <TDITALIC>*</TDITALIC>
     <TDUNDERLIN>*</TDUNDERLIN>
     <LANGU>E</LANGU>
    </SSFPARAS>
    <SSFPARAS>
     <ACTIVE>A</ACTIVE>
     <STYLENAME>ZSDSSD010</STYLENAME>
     <TDPARGRAPH>C4</TDPARGRAPH>
     <TDPJUSTIFY>CENTER</TDPJUSTIFY>
     <TDPLDIST>1.0</TDPLDIST>
     <TDPLDISTU>LN</TDPLDISTU>
     <TDPTOP>1.2</TDPTOP>
     <TDPTOPU>CM</TDPTOPU>
     <TDPBOTU>CM</TDPBOTU>
     <TDPLEFTU>CM</TDPLEFTU>
     <TDPRIGHTU>CM</TDPRIGHTU>
     <TDPENTRYU>CM</TDPENTRYU>
     <TDNUMLEFTU>CM</TDNUMLEFTU>
     <TDFAMILY>THANGSAN</TDFAMILY>
     <TDHEIGHT>120</TDHEIGHT>
     <TDBOLD>*</TDBOLD>
     <TDITALIC>*</TDITALIC>
     <TDUNDERLIN>*</TDUNDERLIN>
     <LANGU>E</LANGU>
    </SSFPARAS>
    <SSFPARAS>
     <ACTIVE>A</ACTIVE>
     <STYLENAME>ZSDSSD010</STYLENAME>
     <TDPARGRAPH>C5</TDPARGRAPH>
     <TDPJUSTIFY>CENTER</TDPJUSTIFY>
     <TDPLDIST>0.6</TDPLDIST>
     <TDPLDISTU>LN</TDPLDISTU>
     <TDPTOPU>CM</TDPTOPU>
     <TDPBOTU>CM</TDPBOTU>
     <TDPLEFTU>CM</TDPLEFTU>
     <TDPRIGHTU>CM</TDPRIGHTU>
     <TDPENTRYU>CM</TDPENTRYU>
     <TDNUMLEFTU>CM</TDNUMLEFTU>
     <TDFAMILY>THANGSAN</TDFAMILY>
     <TDHEIGHT>120</TDHEIGHT>
     <TDBOLD>*</TDBOLD>
     <TDITALIC>*</TDITALIC>
     <TDUNDERLIN>*</TDUNDERLIN>
     <LANGU>E</LANGU>
    </SSFPARAS>
    <SSFPARAS>
     <ACTIVE>A</ACTIVE>
     <STYLENAME>ZSDSSD010</STYLENAME>
     <TDPARGRAPH>C6</TDPARGRAPH>
     <TDPJUSTIFY>CENTER</TDPJUSTIFY>
     <TDPLDIST>1.0</TDPLDIST>
     <TDPLDISTU>LN</TDPLDISTU>
     <TDPTOPU>CM</TDPTOPU>
     <TDPBOTU>CM</TDPBOTU>
     <TDPLEFTU>CM</TDPLEFTU>
     <TDPRIGHTU>CM</TDPRIGHTU>
     <TDPENTRYU>CM</TDPENTRYU>
     <TDNUMLEFTU>CM</TDNUMLEFTU>
     <TDFAMILY>THANGSAN</TDFAMILY>
     <TDHEIGHT>120</TDHEIGHT>
     <TDBOLD>*</TDBOLD>
     <TDITALIC>*</TDITALIC>
     <TDUNDERLIN>*</TDUNDERLIN>
     <LANGU>E</LANGU>
    </SSFPARAS>
    <SSFPARAS>
     <ACTIVE>A</ACTIVE>
     <STYLENAME>ZSDSSD010</STYLENAME>
     <TDPARGRAPH>C7</TDPARGRAPH>
     <TDPJUSTIFY>CENTER</TDPJUSTIFY>
     <TDPLDIST>1.0</TDPLDIST>
     <TDPLDISTU>LN</TDPLDISTU>
     <TDPTOP>0.3</TDPTOP>
     <TDPTOPU>CM</TDPTOPU>
     <TDPBOTU>CM</TDPBOTU>
     <TDPLEFTU>CM</TDPLEFTU>
     <TDPRIGHTU>CM</TDPRIGHTU>
     <TDPENTRYU>CM</TDPENTRYU>
     <TDNUMLEFTU>CM</TDNUMLEFTU>
     <TDFAMILY>THANGSAN</TDFAMILY>
     <TDHEIGHT>500</TDHEIGHT>
     <TDBOLD>X</TDBOLD>
     <TDITALIC>*</TDITALIC>
     <TDUNDERLIN>*</TDUNDERLIN>
     <LANGU>E</LANGU>
    </SSFPARAS>
    <SSFPARAS>
     <ACTIVE>A</ACTIVE>
     <STYLENAME>ZSDSSD010</STYLENAME>
     <TDPARGRAPH>CD</TDPARGRAPH>
     <TDPJUSTIFY>CENTER</TDPJUSTIFY>
     <TDPLDIST>1.0</TDPLDIST>
     <TDPLDISTU>LN</TDPLDISTU>
     <TDPTOPU>CM</TDPTOPU>
     <TDPBOTU>CM</TDPBOTU>
     <TDPLEFTU>CM</TDPLEFTU>
     <TDPRIGHTU>CM</TDPRIGHTU>
     <TDPENTRYU>CM</TDPENTRYU>
     <TDNUMLEFTU>CM</TDNUMLEFTU>
     <TDFAMILY>THANGSAN</TDFAMILY>
     <TDHEIGHT>120</TDHEIGHT>
     <TDBOLD>*</TDBOLD>
     <TDITALIC>*</TDITALIC>
     <TDUNDERLIN>*</TDUNDERLIN>
     <LANGU>E</LANGU>
     <CAPTION>Detail Center</CAPTION>
    </SSFPARAS>
    <SSFPARAS>
     <ACTIVE>A</ACTIVE>
     <STYLENAME>ZSDSSD010</STYLENAME>
     <TDPARGRAPH>F</TDPARGRAPH>
     <TDPJUSTIFY>LEFT</TDPJUSTIFY>
     <TDPLDIST>1.0</TDPLDIST>
     <TDPLDISTU>LN</TDPLDISTU>
     <TDPTOPU>CM</TDPTOPU>
     <TDPBOTU>CM</TDPBOTU>
     <TDPLEFTU>CM</TDPLEFTU>
     <TDPRIGHTU>CM</TDPRIGHTU>
     <TDPENTRYU>CM</TDPENTRYU>
     <TDNUMLEFTU>CM</TDNUMLEFTU>
     <TDFAMILY>THANGSAN</TDFAMILY>
     <TDHEIGHT>120</TDHEIGHT>
     <TDBOLD>*</TDBOLD>
     <TDITALIC>*</TDITALIC>
     <TDUNDERLIN>*</TDUNDERLIN>
     <LANGU>E</LANGU>
     <CAPTION>FOOTER</CAPTION>
    </SSFPARAS>
    <SSFPARAS>
     <ACTIVE>A</ACTIVE>
     <STYLENAME>ZSDSSD010</STYLENAME>
     <TDPARGRAPH>H</TDPARGRAPH>
     <TDPJUSTIFY>LEFT</TDPJUSTIFY>
     <TDPLDIST>1.0</TDPLDIST>
     <TDPLDISTU>LN</TDPLDISTU>
     <TDPTOPU>CM</TDPTOPU>
     <TDPBOTU>CM</TDPBOTU>
     <TDPLEFTU>CM</TDPLEFTU>
     <TDPRIGHTU>CM</TDPRIGHTU>
     <TDPENTRYU>CM</TDPENTRYU>
     <TDNUMLEFTU>CM</TDNUMLEFTU>
     <TDFAMILY>THANGSAN</TDFAMILY>
     <TDHEIGHT>120</TDHEIGHT>
     <TDBOLD>*</TDBOLD>
     <TDITALIC>*</TDITALIC>
     <TDUNDERLIN>*</TDUNDERLIN>
     <LANGU>E</LANGU>
     <CAPTION>Header LEFT</CAPTION>
    </SSFPARAS>
    <SSFPARAS>
     <ACTIVE>A</ACTIVE>
     <STYLENAME>ZSDSSD010</STYLENAME>
     <TDPARGRAPH>H1</TDPARGRAPH>
     <TDPJUSTIFY>LEFT</TDPJUSTIFY>
     <TDPLDIST>1.0</TDPLDIST>
     <TDPLDISTU>LN</TDPLDISTU>
     <TDPTOPU>CM</TDPTOPU>
     <TDPBOTU>CM</TDPBOTU>
     <TDPLEFTU>CM</TDPLEFTU>
     <TDPRIGHTU>CM</TDPRIGHTU>
     <TDPENTRYU>CM</TDPENTRYU>
     <TDNUMLEFTU>CM</TDNUMLEFTU>
     <TDFAMILY>THANGSAN</TDFAMILY>
     <TDHEIGHT>120</TDHEIGHT>
     <TDBOLD>*</TDBOLD>
     <TDITALIC>*</TDITALIC>
     <TDUNDERLIN>*</TDUNDERLIN>
     <LANGU>E</LANGU>
     <CAPTION>Header Right</CAPTION>
    </SSFPARAS>
    <SSFPARAS>
     <ACTIVE>A</ACTIVE>
     <STYLENAME>ZSDSSD010</STYLENAME>
     <TDPARGRAPH>L</TDPARGRAPH>
     <TDPJUSTIFY>LEFT</TDPJUSTIFY>
     <TDPLDIST>1.0</TDPLDIST>
     <TDPLDISTU>LN</TDPLDISTU>
     <TDPTOPU>CM</TDPTOPU>
     <TDPBOTU>CM</TDPBOTU>
     <TDPLEFTU>CM</TDPLEFTU>
     <TDPRIGHTU>CM</TDPRIGHTU>
     <TDPENTRYU>CM</TDPENTRYU>
     <TDNUMLEFTU>CM</TDNUMLEFTU>
     <TDFAMILY>THANGSAN</TDFAMILY>
     <TDHEIGHT>120</TDHEIGHT>
     <TDBOLD>*</TDBOLD>
     <TDITALIC>*</TDITALIC>
     <TDUNDERLIN>*</TDUNDERLIN>
     <LANGU>E</LANGU>
    </SSFPARAS>
    <SSFPARAS>
     <ACTIVE>A</ACTIVE>
     <STYLENAME>ZSDSSD010</STYLENAME>
     <TDPARGRAPH>L1</TDPARGRAPH>
     <TDPJUSTIFY>LEFT</TDPJUSTIFY>
     <TDPLDIST>0.8</TDPLDIST>
     <TDPLDISTU>LN</TDPLDISTU>
     <TDPTOPU>CM</TDPTOPU>
     <TDPBOTU>CM</TDPBOTU>
     <TDPLEFT>0.1</TDPLEFT>
     <TDPLEFTU>CM</TDPLEFTU>
     <TDPRIGHTU>CM</TDPRIGHTU>
     <TDPENTRYU>CM</TDPENTRYU>
     <TDNUMLEFTU>CM</TDNUMLEFTU>
     <TDFAMILY>THANGSAN</TDFAMILY>
     <TDHEIGHT>120</TDHEIGHT>
     <TDBOLD>*</TDBOLD>
     <TDITALIC>*</TDITALIC>
     <TDUNDERLIN>*</TDUNDERLIN>
     <LANGU>E</LANGU>
    </SSFPARAS>
    <SSFPARAS>
     <ACTIVE>A</ACTIVE>
     <STYLENAME>ZSDSSD010</STYLENAME>
     <TDPARGRAPH>L2</TDPARGRAPH>
     <TDPJUSTIFY>LEFT</TDPJUSTIFY>
     <TDPLDIST>0.8</TDPLDIST>
     <TDPLDISTU>LN</TDPLDISTU>
     <TDPTOP>0.15</TDPTOP>
     <TDPTOPU>CM</TDPTOPU>
     <TDPBOTU>CM</TDPBOTU>
     <TDPLEFT>0.1</TDPLEFT>
     <TDPLEFTU>CM</TDPLEFTU>
     <TDPRIGHTU>CM</TDPRIGHTU>
     <TDPENTRYU>CM</TDPENTRYU>
     <TDNUMLEFTU>CM</TDNUMLEFTU>
     <TDFAMILY>THANGSAN</TDFAMILY>
     <TDHEIGHT>120</TDHEIGHT>
     <TDBOLD>*</TDBOLD>
     <TDITALIC>*</TDITALIC>
     <TDUNDERLIN>*</TDUNDERLIN>
     <LANGU>E</LANGU>
    </SSFPARAS>
    <SSFPARAS>
     <ACTIVE>A</ACTIVE>
     <STYLENAME>ZSDSSD010</STYLENAME>
     <TDPARGRAPH>L3</TDPARGRAPH>
     <TDPJUSTIFY>LEFT</TDPJUSTIFY>
     <TDPLDIST>1.0</TDPLDIST>
     <TDPLDISTU>LN</TDPLDISTU>
     <TDPTOP>0.2</TDPTOP>
     <TDPTOPU>CM</TDPTOPU>
     <TDPBOTU>CM</TDPBOTU>
     <TDPLEFT>0.1</TDPLEFT>
     <TDPLEFTU>CM</TDPLEFTU>
     <TDPRIGHTU>CM</TDPRIGHTU>
     <TDPENTRYU>CM</TDPENTRYU>
     <TDNUMLEFTU>CM</TDNUMLEFTU>
     <TDFAMILY>THANGSAN</TDFAMILY>
     <TDHEIGHT>120</TDHEIGHT>
     <TDBOLD>*</TDBOLD>
     <TDITALIC>*</TDITALIC>
     <TDUNDERLIN>*</TDUNDERLIN>
     <LANGU>E</LANGU>
    </SSFPARAS>
    <SSFPARAS>
     <ACTIVE>A</ACTIVE>
     <STYLENAME>ZSDSSD010</STYLENAME>
     <TDPARGRAPH>L4</TDPARGRAPH>
     <TDPJUSTIFY>LEFT</TDPJUSTIFY>
     <TDPLDIST>1.0</TDPLDIST>
     <TDPLDISTU>LN</TDPLDISTU>
     <TDPTOP>0.2</TDPTOP>
     <TDPTOPU>CM</TDPTOPU>
     <TDPBOTU>CM</TDPBOTU>
     <TDPLEFT>0.1</TDPLEFT>
     <TDPLEFTU>CM</TDPLEFTU>
     <TDPRIGHTU>CM</TDPRIGHTU>
     <TDPENTRYU>CM</TDPENTRYU>
     <TDNUMLEFTU>CM</TDNUMLEFTU>
     <TDFAMILY>THANGSAN</TDFAMILY>
     <TDHEIGHT>120</TDHEIGHT>
     <TDBOLD>*</TDBOLD>
     <TDITALIC>*</TDITALIC>
     <TDUNDERLIN>*</TDUNDERLIN>
     <LANGU>E</LANGU>
    </SSFPARAS>
    <SSFPARAS>
     <ACTIVE>A</ACTIVE>
     <STYLENAME>ZSDSSD010</STYLENAME>
     <TDPARGRAPH>L5</TDPARGRAPH>
     <TDPJUSTIFY>LEFT</TDPJUSTIFY>
     <TDPLDIST>1.0</TDPLDIST>
     <TDPLDISTU>LN</TDPLDISTU>
     <TDPTOP>1.3</TDPTOP>
     <TDPTOPU>CM</TDPTOPU>
     <TDPBOTU>CM</TDPBOTU>
     <TDPLEFT>0.1</TDPLEFT>
     <TDPLEFTU>CM</TDPLEFTU>
     <TDPRIGHTU>CM</TDPRIGHTU>
     <TDPENTRYU>CM</TDPENTRYU>
     <TDNUMLEFTU>CM</TDNUMLEFTU>
     <TDFAMILY>THANGSAN</TDFAMILY>
     <TDHEIGHT>120</TDHEIGHT>
     <TDBOLD>*</TDBOLD>
     <TDITALIC>*</TDITALIC>
     <TDUNDERLIN>*</TDUNDERLIN>
     <LANGU>E</LANGU>
    </SSFPARAS>
    <SSFPARAS>
     <ACTIVE>A</ACTIVE>
     <STYLENAME>ZSDSSD010</STYLENAME>
     <TDPARGRAPH>L6</TDPARGRAPH>
     <TDPJUSTIFY>LEFT</TDPJUSTIFY>
     <TDPLDIST>1.0</TDPLDIST>
     <TDPLDISTU>LN</TDPLDISTU>
     <TDPTOPU>CM</TDPTOPU>
     <TDPBOTU>CM</TDPBOTU>
     <TDPLEFT>1.3</TDPLEFT>
     <TDPLEFTU>CM</TDPLEFTU>
     <TDPRIGHTU>CM</TDPRIGHTU>
     <TDPENTRYU>CM</TDPENTRYU>
     <TDNUMLEFTU>CM</TDNUMLEFTU>
     <TDFAMILY>THANGSAN</TDFAMILY>
     <TDHEIGHT>120</TDHEIGHT>
     <TDBOLD>*</TDBOLD>
     <TDITALIC>*</TDITALIC>
     <TDUNDERLIN>*</TDUNDERLIN>
     <LANGU>E</LANGU>
    </SSFPARAS>
    <SSFPARAS>
     <ACTIVE>A</ACTIVE>
     <STYLENAME>ZSDSSD010</STYLENAME>
     <TDPARGRAPH>L7</TDPARGRAPH>
     <TDPJUSTIFY>LEFT</TDPJUSTIFY>
     <TDPLDIST>1.0</TDPLDIST>
     <TDPLDISTU>LN</TDPLDISTU>
     <TDPTOPU>CM</TDPTOPU>
     <TDPBOTU>CM</TDPBOTU>
     <TDPLEFT>0.1</TDPLEFT>
     <TDPLEFTU>CM</TDPLEFTU>
     <TDPRIGHTU>CM</TDPRIGHTU>
     <TDPENTRYU>CM</TDPENTRYU>
     <TDNUMLEFTU>CM</TDNUMLEFTU>
     <TDFAMILY>THANGSAN</TDFAMILY>
     <TDHEIGHT>120</TDHEIGHT>
     <TDBOLD>*</TDBOLD>
     <TDITALIC>*</TDITALIC>
     <TDUNDERLIN>*</TDUNDERLIN>
     <LANGU>E</LANGU>
    </SSFPARAS>
    <SSFPARAS>
     <ACTIVE>A</ACTIVE>
     <STYLENAME>ZSDSSD010</STYLENAME>
     <TDPARGRAPH>L8</TDPARGRAPH>
     <TDPJUSTIFY>LEFT</TDPJUSTIFY>
     <TDPLDIST>0.8</TDPLDIST>
     <TDPLDISTU>LN</TDPLDISTU>
     <TDPTOPU>CM</TDPTOPU>
     <TDPBOTU>CM</TDPBOTU>
     <TDPLEFT>0.1</TDPLEFT>
     <TDPLEFTU>CM</TDPLEFTU>
     <TDPRIGHTU>CM</TDPRIGHTU>
     <TDPENTRYU>CM</TDPENTRYU>
     <TDNUMLEFTU>CM</TDNUMLEFTU>
     <TDFAMILY>THANGSAN</TDFAMILY>
     <TDHEIGHT>100</TDHEIGHT>
     <TDBOLD>X</TDBOLD>
     <TDITALIC>*</TDITALIC>
     <TDUNDERLIN>*</TDUNDERLIN>
     <LANGU>E</LANGU>
    </SSFPARAS>
    <SSFPARAS>
     <ACTIVE>A</ACTIVE>
     <STYLENAME>ZSDSSD010</STYLENAME>
     <TDPARGRAPH>LD</TDPARGRAPH>
     <TDPJUSTIFY>LEFT</TDPJUSTIFY>
     <TDPLDIST>1.0</TDPLDIST>
     <TDPLDISTU>LN</TDPLDISTU>
     <TDPTOPU>CM</TDPTOPU>
     <TDPBOTU>CM</TDPBOTU>
     <TDPLEFTU>CM</TDPLEFTU>
     <TDPRIGHTU>CM</TDPRIGHTU>
     <TDPENTRYU>CM</TDPENTRYU>
     <TDNUMLEFTU>CM</TDNUMLEFTU>
     <TDFAMILY>THANGSAN</TDFAMILY>
     <TDHEIGHT>120</TDHEIGHT>
     <TDBOLD>*</TDBOLD>
     <TDITALIC>*</TDITALIC>
     <TDUNDERLIN>*</TDUNDERLIN>
     <LANGU>E</LANGU>
     <CAPTION>Detail left</CAPTION>
    </SSFPARAS>
    <SSFPARAS>
     <ACTIVE>A</ACTIVE>
     <STYLENAME>ZSDSSD010</STYLENAME>
     <TDPARGRAPH>LF</TDPARGRAPH>
     <TDPJUSTIFY>LEFT</TDPJUSTIFY>
     <TDPLDIST>1.0</TDPLDIST>
     <TDPLDISTU>LN</TDPLDISTU>
     <TDPTOPU>CM</TDPTOPU>
     <TDPBOTU>CM</TDPBOTU>
     <TDPLEFT>0.2</TDPLEFT>
     <TDPLEFTU>CM</TDPLEFTU>
     <TDPRIGHTU>CM</TDPRIGHTU>
     <TDPENTRYU>CM</TDPENTRYU>
     <TDNUMLEFTU>CM</TDNUMLEFTU>
     <TDFAMILY>THANGSAN</TDFAMILY>
     <TDHEIGHT>120</TDHEIGHT>
     <TDBOLD>*</TDBOLD>
     <TDITALIC>*</TDITALIC>
     <TDUNDERLIN>*</TDUNDERLIN>
     <LANGU>E</LANGU>
     <CAPTION>LEFT with SPACE</CAPTION>
    </SSFPARAS>
    <SSFPARAS>
     <ACTIVE>A</ACTIVE>
     <STYLENAME>ZSDSSD010</STYLENAME>
     <TDPARGRAPH>P</TDPARGRAPH>
     <TDPJUSTIFY>CENTER</TDPJUSTIFY>
     <TDPLDIST>1.0</TDPLDIST>
     <TDPLDISTU>LN</TDPLDISTU>
     <TDPTOPU>CM</TDPTOPU>
     <TDPBOTU>CM</TDPBOTU>
     <TDPLEFTU>CM</TDPLEFTU>
     <TDPRIGHTU>CM</TDPRIGHTU>
     <TDPENTRYU>CM</TDPENTRYU>
     <TDNUMLEFTU>CM</TDNUMLEFTU>
     <TDFAMILY>THANGSAN</TDFAMILY>
     <TDHEIGHT>120</TDHEIGHT>
     <TDBOLD>*</TDBOLD>
     <TDITALIC>*</TDITALIC>
     <TDUNDERLIN>*</TDUNDERLIN>
     <LANGU>E</LANGU>
    </SSFPARAS>
    <SSFPARAS>
     <ACTIVE>A</ACTIVE>
     <STYLENAME>ZSDSSD010</STYLENAME>
     <TDPARGRAPH>R</TDPARGRAPH>
     <TDPJUSTIFY>LEFT</TDPJUSTIFY>
     <TDPLDIST>1.0</TDPLDIST>
     <TDPLDISTU>LN</TDPLDISTU>
     <TDPTOPU>CM</TDPTOPU>
     <TDPBOTU>CM</TDPBOTU>
     <TDPLEFTU>CM</TDPLEFTU>
     <TDPRIGHTU>CM</TDPRIGHTU>
     <TDPENTRYU>CM</TDPENTRYU>
     <TDNUMLEFTU>CM</TDNUMLEFTU>
     <TDFAMILY>THANGSAN</TDFAMILY>
     <TDHEIGHT>120</TDHEIGHT>
     <TDBOLD>*</TDBOLD>
     <TDITALIC>*</TDITALIC>
     <TDUNDERLIN>*</TDUNDERLIN>
     <LANGU>E</LANGU>
     <CAPTION>Remark</CAPTION>
    </SSFPARAS>
    <SSFPARAS>
     <ACTIVE>A</ACTIVE>
     <STYLENAME>ZSDSSD010</STYLENAME>
     <TDPARGRAPH>R1</TDPARGRAPH>
     <TDPJUSTIFY>LEFT</TDPJUSTIFY>
     <TDPLDIST>1.0</TDPLDIST>
     <TDPLDISTU>LN</TDPLDISTU>
     <TDPTOPU>CM</TDPTOPU>
     <TDPBOTU>CM</TDPBOTU>
     <TDPLEFTU>CM</TDPLEFTU>
     <TDPRIGHTU>CM</TDPRIGHTU>
     <TDPENTRYU>CM</TDPENTRYU>
     <TDNUMLEFTU>CM</TDNUMLEFTU>
     <TDFAMILY>THANGSAN</TDFAMILY>
     <TDHEIGHT>120</TDHEIGHT>
     <TDBOLD>*</TDBOLD>
     <TDITALIC>*</TDITALIC>
     <TDUNDERLIN>*</TDUNDERLIN>
     <LANGU>E</LANGU>
     <CAPTION>INV Remark</CAPTION>
    </SSFPARAS>
    <SSFPARAS>
     <ACTIVE>A</ACTIVE>
     <STYLENAME>ZSDSSD010</STYLENAME>
     <TDPARGRAPH>R2</TDPARGRAPH>
     <TDPJUSTIFY>RIGHT</TDPJUSTIFY>
     <TDPLDIST>1.0</TDPLDIST>
     <TDPLDISTU>LN</TDPLDISTU>
     <TDPTOPU>CM</TDPTOPU>
     <TDPBOTU>CM</TDPBOTU>
     <TDPLEFTU>CM</TDPLEFTU>
     <TDPRIGHTU>CM</TDPRIGHTU>
     <TDPENTRYU>CM</TDPENTRYU>
     <TDNUMLEFTU>CM</TDNUMLEFTU>
     <TDBOLD>*</TDBOLD>
     <TDITALIC>*</TDITALIC>
     <TDUNDERLIN>*</TDUNDERLIN>
     <LANGU>E</LANGU>
    </SSFPARAS>
    <SSFPARAS>
     <ACTIVE>A</ACTIVE>
     <STYLENAME>ZSDSSD010</STYLENAME>
     <TDPARGRAPH>R3</TDPARGRAPH>
     <TDPJUSTIFY>RIGHT</TDPJUSTIFY>
     <TDPLDIST>1.0</TDPLDIST>
     <TDPLDISTU>LN</TDPLDISTU>
     <TDPTOPU>CM</TDPTOPU>
     <TDPBOTU>CM</TDPBOTU>
     <TDPLEFTU>CM</TDPLEFTU>
     <TDPRIGHT>0.3</TDPRIGHT>
     <TDPRIGHTU>CM</TDPRIGHTU>
     <TDPENTRYU>CM</TDPENTRYU>
     <TDNUMLEFTU>CM</TDNUMLEFTU>
     <TDFAMILY>THANGSAN</TDFAMILY>
     <TDHEIGHT>120</TDHEIGHT>
     <TDBOLD>*</TDBOLD>
     <TDITALIC>*</TDITALIC>
     <TDUNDERLIN>*</TDUNDERLIN>
     <LANGU>E</LANGU>
    </SSFPARAS>
    <SSFPARAS>
     <ACTIVE>A</ACTIVE>
     <STYLENAME>ZSDSSD010</STYLENAME>
     <TDPARGRAPH>RD</TDPARGRAPH>
     <TDPJUSTIFY>RIGHT</TDPJUSTIFY>
     <TDPLDIST>1.0</TDPLDIST>
     <TDPLDISTU>LN</TDPLDISTU>
     <TDPTOPU>CM</TDPTOPU>
     <TDPBOTU>CM</TDPBOTU>
     <TDPLEFTU>CM</TDPLEFTU>
     <TDPRIGHTU>CM</TDPRIGHTU>
     <TDPENTRYU>CM</TDPENTRYU>
     <TDNUMLEFTU>CM</TDNUMLEFTU>
     <TDFAMILY>THANGSAN</TDFAMILY>
     <TDHEIGHT>120</TDHEIGHT>
     <TDBOLD>*</TDBOLD>
     <TDITALIC>*</TDITALIC>
     <TDUNDERLIN>*</TDUNDERLIN>
     <LANGU>E</LANGU>
     <CAPTION>Detail RIGHT</CAPTION>
    </SSFPARAS>
   </SSFPARAS>
   <SSFSTRINGS>
    <SSFSTRINGS>
     <ACTIVE>A</ACTIVE>
     <STYLENAME>ZSDSSD010</STYLENAME>
     <TDSTRING>BC</TDSTRING>
     <TDSUPER>*</TDSUPER>
     <TDSUB>*</TDSUB>
     <TDHIDDEN>*</TDHIDDEN>
     <TDPROTLINE>*</TDPROTLINE>
     <TDBARCODE>ZSDSPKA4</TDBARCODE>
     <TDBOLD>*</TDBOLD>
     <TDITALIC>*</TDITALIC>
     <TDUNDERLIN>*</TDUNDERLIN>
     <LANGU>E</LANGU>
     <CAPTION>Barcode</CAPTION>
    </SSFSTRINGS>
    <SSFSTRINGS>
     <ACTIVE>A</ACTIVE>
     <STYLENAME>ZSDSSD010</STYLENAME>
     <TDSTRING>QR</TDSTRING>
     <TDSUPER>*</TDSUPER>
     <TDSUB>*</TDSUB>
     <TDHIDDEN>*</TDHIDDEN>
     <TDPROTLINE>*</TDPROTLINE>
     <TDBARCODE>ZSDSQR</TDBARCODE>
     <TDBOLD>*</TDBOLD>
     <TDITALIC>*</TDITALIC>
     <TDUNDERLIN>*</TDUNDERLIN>
     <LANGU>E</LANGU>
    </SSFSTRINGS>
   </SSFSTRINGS>
  </asx:values>
 </asx:abap>
</abapGit>
